[
  {
    "Tag": "General Information",
    "Url": "/blog/tags/General-Information.html",
    "Weight": 9
  },
  {
    "Tag": "Investment",
    "Url": "/blog/tags/Investment.html",
    "Weight": 6
  },
  {
    "Tag": "Buy",
    "Url": "/blog/tags/Buy.html",
    "Weight": 6
  },
  {
    "Tag": "Sell",
    "Url": "/blog/tags/Sell.html",
    "Weight": 5
  },
  {
    "Tag": "News",
    "Url": "/blog/tags/News.html",
    "Weight": 4
  },
  {
    "Tag": "NEWS",
    "Url": "/blog/tags/NEWS.html",
    "Weight": 3
  },
  {
    "Tag": "Where I Live",
    "Url": "/blog/tags/Where-I-Live.html",
    "Weight": 3
  },
  {
    "Tag": "Krakow",
    "Url": "/blog/tags/Krakow.html",
    "Weight": 3
  },
  {
    "Tag": "Let",
    "Url": "/blog/tags/Let.html",
    "Weight": 2
  },
  {
    "Tag": "Rent",
    "Url": "/blog/tags/Rent.html",
    "Weight": 2
  },
  {
    "Tag": "news",
    "Url": "/blog/tags/news.html",
    "Weight": 2
  },
  {
    "Tag": "Wlochy",
    "Url": "/blog/tags/Wlochy.html",
    "Weight": 1
  },
  {
    "Tag": "Warsaw",
    "Url": "/blog/tags/Warsaw.html",
    "Weight": 1
  },
  {
    "Tag": "Rzaska",
    "Url": "/blog/tags/Rzaska.html",
    "Weight": 1
  },
  {
    "Tag": "Szczecin",
    "Url": "/blog/tags/Szczecin.html",
    "Weight": 1
  },
  {
    "Tag": "Rzeszow",
    "Url": "/blog/tags/Rzeszow.html",
    "Weight": 1
  },
  {
    "Tag": "Airbnb",
    "Url": "/blog/tags/Airbnb.html",
    "Weight": 1
  },
  {
    "Tag": "Katowice",
    "Url": "/blog/tags/Katowice.html",
    "Weight": 1
  },
  {
    "Tag": "INVESTMENT",
    "Url": "/blog/tags/INVESTMENT.html",
    "Weight": 1
  },
  {
    "Tag": "let",
    "Url": "/blog/tags/let.html",
    "Weight": 1
  },
  {
    "Tag": "Valuation",
    "Url": "/blog/tags/Valuation.html",
    "Weight": 1
  },
  {
    "Tag": "Suburb West",
    "Url": "/blog/tags/Suburb-West.html",
    "Weight": 1
  },
  {
    "Tag": "Torun",
    "Url": "/blog/tags/Torun.html",
    "Weight": 1
  },
  {
    "Tag": "Opole",
    "Url": "/blog/tags/Opole.html",
    "Weight": 1
  },
  {
    "Tag": "Statistics",
    "Url": "/blog/tags/Statistics.html",
    "Weight": 1
  },
  {
    "Tag": "Gdansk",
    "Url": "/blog/tags/Gdansk.html",
    "Weight": 1
  },
  {
    "Tag": "LET",
    "Url": "/blog/tags/LET.html",
    "Weight": 1
  },
  {
    "Tag": "RENT",
    "Url": "/blog/tags/RENT.html",
    "Weight": 1
  },
  {
    "Tag": "rent",
    "Url": "/blog/tags/rent.html",
    "Weight": 1
  },
  {
    "Tag": "Home Loan",
    "Url": "/blog/tags/Home-Loan.html",
    "Weight": 1
  },
  {
    "Tag": "Zabierzow",
    "Url": "/blog/tags/Zabierzow.html",
    "Weight": 1
  },
  {
    "Tag": "Poznan",
    "Url": "/blog/tags/Poznan.html",
    "Weight": 1
  },
  {
    "Tag": "Olsztyn",
    "Url": "/blog/tags/Olsztyn.html",
    "Weight": 1
  },
  {
    "Tag": "Lublin",
    "Url": "/blog/tags/Lublin.html",
    "Weight": 1
  },
  {
    "Tag": "Lodz",
    "Url": "/blog/tags/Lodz.html",
    "Weight": 1
  },
  {
    "Tag": "Kielce",
    "Url": "/blog/tags/Kielce.html",
    "Weight": 1
  },
  {
    "Tag": "Bydgoszcz",
    "Url": "/blog/tags/Bydgoszcz.html",
    "Weight": 1
  },
  {
    "Tag": "Bialystok",
    "Url": "/blog/tags/Bialystok.html",
    "Weight": 1
  },
  {
    "Tag": "LODZ",
    "Url": "/blog/tags/LODZ.html",
    "Weight": 1
  }
]